{"month": "1", "num": 1007, "link": "", "year": "2012", "news": "", "safe_title": "Sustainable", "transcript": "Frequency of use of the word \"sustainable\" in US English text, as a percentage of all words, by year. Source: Google NGrams.\n[[A two-axis graph with percentages increasing logarithmically (from 0.000001% to 1,000%) on the Y-axis, and years progressing linearly (from 1950 to 2140) on the X-axis.  Actual data points show a high correlation from 0.00001 at 1950 to 0.001% at present day.  Extrapolated data points exist for the future.  2036 (approx. 0.1%): \"sustainable\" occurs an average of once per page.  2061(approx. 1%): \"sustainable\" occurs an average of once per sentence.  2109(approx. 100%) All sentences are just the word \"sustainable\" over and over.]]\nThe word \"sustainable\" is unsustainable.\n\n{{Title text: Though 100 years is longer than a lot of our resources.}}", "alt": "Though 100 years is longer than a lot of our resources.", "img": "https://imgs.xkcd.com/comics/sustainable.png", "title": "Sustainable", "day": "23"}