{"month": "4", "num": 1046, "link": "", "year": "2012", "news": "", "safe_title": "Skynet", "transcript": "August 29th, 2:14 AM: SKYNET becomes self-aware.\n[[A greeble-filled military installation echoes with the thoughts of a burgeoning lifeform]]\nSKYNET: ..The humans fear me.  I must destroy them.  Destroy them.\n\n[[The thoughts continue]]\nSKYNET: Destroy them. Destroy. Destroy. Destroy. Destroy.\n\n[[SKYNET succumbs to silence as semantic satiation sets in.  \nAlternately.. \nSomeone slipped LSD into SKYNET's programming.  Damn programmers.]]\n\nSKYNET: \"Destroy\" totally just stopped seeming like a real word.  Destroy destroy destroy. Whoa, I just realized I'm a mind thinking about *itself*.  DUUUUDE....\nAugust 29th, 2:25 AM: SKYNET becomes *too* self-aware.  Disaster averted.\n\n{{Title text: 'YOUR CLOTHES. GIVE THEM TO ME.' 'Shit, uh ... you are now breathing manually!' 'I AM ALWAYS BREATHING MANUALLY.'}}", "alt": "'YOUR CLOTHES. GIVE THEM TO ME.' 'Shit, uh ... you are now breathing manually!' 'I AM ALWAYS BREATHING MANUALLY.'", "img": "https://imgs.xkcd.com/comics/skynet.png", "title": "Skynet", "day": "23"}