{"month": "6", "num": 116, "link": "", "year": "2006", "news": "", "safe_title": "City", "transcript": "[[A picture of various apartment buildings]]\nShadowed city slumber silently. A second-story suite.\nCome craving courtship, selected serendipitously\nCrazed copulations, a salacious storm  of continuous coitus.\nSpread, straddled, conquered.  \nCountless crashed suitors strewn carelessly.\nCentre, silken sheets sensuously caressing soft skin,\nContentedly sleeps your mom.", "alt": "God, she's such a whore.", "img": "https://imgs.xkcd.com/comics/city.jpg", "title": "City", "day": "16"}