{"month": "3", "num": 1189, "link": "", "year": "2013", "news": "", "safe_title": "Voyager 1", "transcript": "Number of times Voyager 1 has left the solar system.\n[[tally marks indicating 22]]\n\n{{Title text: So far Voyager 1 has 'left the Solar System' by passing through the termination shock three times, the heliopause twice, and once each through the heliosheath, heliosphere, heliodrome, auroral discontinuity, Heaviside layer, trans-Neptunian panic zone, magnetogap, US Census Bureau Solar System statistical boundary, Kuiper gauntlet, Oort void, and crystal sphere holding the fixed stars.}}", "alt": "So far Voyager 1 has 'left the Solar System' by passing through the termination shock three times, the heliopause twice, and once each through the heliosheath, heliosphere, heliodrome, auroral discontinuity, Heaviside layer, trans-Neptunian panic zone, magnetogap, US Census Bureau Solar System statistical boundary, Kuiper gauntlet, Oort void, and crystal sphere holding the fixed stars.", "img": "https://imgs.xkcd.com/comics/voyager_1.png", "title": "Voyager 1", "day": "22"}