{"month": "8", "num": 1253, "link": "", "year": "2013", "news": "", "safe_title": "Exoplanet Names", "transcript": "August 2013: The Internation Astronomical Union decides to start naming exoplanets, and - for the first time ever - asks for suggestions from the general public. \nThey immediately regret this decision.\n[[Four figures stand around looking at a computer screen. One is facepalming.]]\nMan: Can't you filter out the worst ones? \nWoman: This is *after* the filter!\n\n((The list of suggestions is given as a table with three columns: \"Star\", \"Planet\", \"Suggested Name\". Here, the columns are given in a |-delimited form.))\nStar | Planet | Suggested Name\nGliese 667C | b | Space planet\nGliese 667C | c | Pilf\nGliese 667C | d | A star\nGliese 667C | e | e'); DROP TABLE planets; --\nGliese 667C | f | Blogosphere\nGliese 667C | g | Blogodrome\nGliese 667C | h | Earth\nTau Ceti | b | Sid Meier's Tau Ceti B\nTau Ceti | c | Giant dog planet\nTau Ceti | d | Tiny dog planet\nTau Ceti | e | Phil plainet\nTau Ceti | f | Unicode snowman\nGliese 832 | b | Asshole Jupiter\nGliese 581 | b | Waist-deep cats\nGliese 581 | c | Planet #14\nGliese 581 | d | Ballderaan\nGliese 581 | e | Eternia prime\nGliese 581 | f | Taupe Mars\nGliese 581 | g | Jelly-filled planet\nEpsilon Eridani | b | Skydot\nEpsilon Eridani | c | Laser noises\nGliese 176 | b | Pandora\nGliese 176 | c | Pantera\nKepler-61 | b | Goldenpalace.com\nUpsilon Andromidae | c | Stampy\nUpsilon Andromidae | d | Moonchild\nUpsilon Andromidae | e | Ham sphere\nHD 20794 | b | Cosmic sands\nHD 20794 | c | Legoland\nHD 20794 | d | Planet with arms\nHD 85512 | b | Lax morality\nHD 40307 | b | Good planet\nHD 40307 | c | Problemland\nHD 40307 | d | Slickle\nHD 40307 | e | Spare parts\nHD 40307 | f | New Jersey VI \nHD 40307 | g | Hod do I join the IAU\nGliese 163 | b | Neil Tyson's mustache\nGliese 163 | c | help@gmail.com\nGliese 163 | d | Hair-covered planet\nPi Mensae | b | Moon holder\nHD 189733 | b | Permadeath\nKepler-22 | b | Blue ivy\nKepler-3284 | b | Blainsley\nKepler-3255 | b | Unicorn thresher\nKepler-2418 | b | Spherical Discworld\nKepler-1686 | b | Emergency backup Earth\nKepler-3010 | b | Feeeooooooooop\nKepler-4742 | b | Liz\n\n{{Title text: If you have any ideas, I hear you can send them to iaupublic@iap.fr.}}", "alt": "If you have any ideas, I hear you can send them to iaupublic@iap.fr.", "img": "https://imgs.xkcd.com/comics/exoplanet_names.png", "title": "Exoplanet Names", "day": "19"}