{"month": "12", "num": 1301, "link": "", "year": "2013", "news": "", "safe_title": "File Extensions", "transcript": "Trustworthiness of information by file extension\n\n[[A series of ordered horizontal bars, most of which extend off to the right, with labels on the left. In order, they are .tex, .pdf, .csv, .txt, .svg, .xls\n.xlsx, .doc, .png, .ppt, .jpg, .jpeg, .gif - with the final two (.jpeg and .gif) extending to the left instead, as if intended to be negative values.]]\n\n{{Title text: I have never been lied to by data in a .txt file which has been hand-aligned.}}", "alt": "I have never been lied to by data in a .txt file which has been hand-aligned.", "img": "https://imgs.xkcd.com/comics/file_extensions.png", "title": "File Extensions", "day": "9"}