{"month": "9", "num": 1425, "link": "", "year": "2014", "news": "", "safe_title": "Tasks", "transcript": "[[A figure stands behind a woman sitting at a desk with a computer on it.]]\nFigure: When a user takes a photo, the app should check whether they're in a national park...\nWoman programmer: Sure, easy GIS lookup. Gimme a few hours. \nFigure: ... and check whether the photo is of a bird. \nWoman programmer: I'll need a research team and five years.\nIn CS, it can be hard to explain the difference between the easy and the virtually impossible.\n\n{{Title text: In the 60s, Marvin Minsky assigned a couple of undergrads to spend the summer programming a computer to use a camera to identify objects in a scene. He figured they'd have the problem solved by the end of the summer. Half a century later, we're still working on it.}}", "alt": "In the 60s, Marvin Minsky assigned a couple of undergrads to spend the summer programming a computer to use a camera to identify objects in a scene. He figured they'd have the problem solved by the end of the summer. Half a century later, we're still working on it.", "img": "https://imgs.xkcd.com/comics/tasks.png", "title": "Tasks", "day": "24"}