{"month": "11", "num": 1607, "link": "", "year": "2015", "news": "", "safe_title": "Supreme Court", "transcript": "[[A news reader sits at a desk. A graphic of the Scales of Justice floats beside her head.]]\nNewsreader: Breaking news: the Supreme Court has ruled 9-1 that they don't know who this guy is or how he got in here, but he's definitely \nnot\n a justice.\n\n{{Title text: Writing for the majority, Justice Kennedy called the man's arguments that he could be either Alito or Ginsburg \"surprisingly compelling, but ultimately unconvincing.\"}}", "alt": "Writing for the majority, Justice Kennedy called the man's arguments that he could be either Alito or Ginsburg \"surprisingly compelling, but ultimately unconvincing.\"", "img": "https://imgs.xkcd.com/comics/supreme_court.png", "title": "Supreme Court", "day": "23"}