{"month": "7", "num": 296, "link": "", "year": "2007", "news": "", "safe_title": "Tony Hawk", "transcript": "My Hobby:\nDoing skateboard tricks in Tony Hawk while also doing them in real life.\n[[Man riding a skateboard in a halfpipe with a handheld video game]]\n<<beep click beep>>\n[[Man does a skateboard trick]]\n<<Frontside 360\u00b0!>>\nVideogame: Frontside 360\u00b0!\n{{Bad idea #271: Dropping into the half-pipe on a Segway.}}", "alt": "Bad idea #271: Dropping into the half-pipe on a Segway.", "img": "https://imgs.xkcd.com/comics/tony_hawk.png", "title": "Tony Hawk", "day": "30"}