{"month": "1", "num": 32, "link": "", "year": "2006", "news": "", "safe_title": "Pillar", "transcript": "This one is mostly by my little brother, Doug.\n[[Person on a tall pillar is talking to person on the group]]\nPerson on pillar: The sky is so blue, and all the leaves are green.\nPerson on ground: Haven' t you ever wondered if we really see the same colors as everyone else? It's all perception.\nPerson on pillar: Well, you might as well call into question all of human experience. Who really knows what world someone else sees?\nPerson on ground: Yeah, I guess.\nPerson on pillar: Anyway, can you help me down from this pole?\nPerson on ground: What pole?\n{{Title Text: A comic by my brother Doug, redrawn and rewritten by me}}", "alt": "A comic by my brother Doug, redrawn and rewritten by me", "img": "https://imgs.xkcd.com/comics/pillar.jpg", "title": "Pillar", "day": "1"}