{"month": "1", "num": 49, "link": "", "year": "2006", "news": "", "safe_title": "Want", "transcript": "I want to be brave enough to tell you how I feel.\nI want to say \"I love you\" _before_ I hang up the phone for once.\nI want to drive all night with you, listening to mix tapes, not caring where we end up.\nOh, and I also really want to get with your sister.\nI mean, DAMN.\n{{title text: Well, she's pretty hot.}}", "alt": "Well, she's pretty hot.", "img": "https://imgs.xkcd.com/comics/want.jpg", "title": "Want", "day": "14"}