{"month": "12", "num": 516, "link": "", "year": "2008", "news": "", "safe_title": "Wood Chips", "transcript": "[[Man leans on desk; Woman sits behind desk.]]\nMan: Did you ever figure out those mysterious woodchips?\nWoman: The ones in the hallway? No.\nMan: You didn't suspect that they matched the timber used in 1861 to build the \"ghost ship\" Mary Celeste, prompting you to send them to a lab for analysis, the results of which raised new and stranger questions?\nWoman: No, I threw them out. Why?\n{{My hoaxes need to get a lot less subtle.}}\n{{alt-text: You didn't run a chemical analysis against the Shroud of Turin? Man, all that work for NOTHING.}}", "alt": "You didn't run a chemical analysis against the Shroud of Turin?  Man, all that work for NOTHING.", "img": "https://imgs.xkcd.com/comics/wood_chips.png", "title": "Wood Chips", "day": "12"}