{"month": "11", "num": 823, "link": "", "year": "2010", "news": "Guest week! Today's comic is contributed by <a href=\"http://www.buttercupfestival.com\">David Troupes</a>.<br />Five guest comics this week! XKCD should be back to normal after that.", "safe_title": "Guest Week: David Troupes (Buttercup Festival)", "transcript": "[[Two people are leaning against each other, sitting on top of the moon.  Trees are visible towards the bottom of the panel.]]\n\n[[The scene broadens.]]\nWoman: I've never been so happy.  I --\nMan: Hold on -- that guy used to dump my notebooks in high school.  Give me a moment.  Try to keep the moon steady.\n\n[[A rock hits someone on the ground on the back of the head.]]\n\n[[The person clutches the back of their head.]]\n\n[[The moon, again.]]\nGuy: I've never been so happy.\n\n{{Title text: Guest comic by David Troupes of Buttercup Festival, who is living in that lovely tree outside your window.}}", "alt": "Guest comic by David Troupes of Buttercup Festival, who is living in that lovely tree outside your window.", "img": "https://imgs.xkcd.com/comics/guest_week_david_troupes_buttercup_festival.png", "title": "Guest Week: David Troupes (Buttercup Festival)", "day": "23"}