{"month": "4", "num": 885, "link": "", "year": "2011", "news": "", "safe_title": "Recycling", "transcript": "[[A person is picking through various items of trash or recycling on a conveyor belt.  A juice bottle, emty cardboard box, opened tin can, bottlecap, crumpled and flat sheets of paper, a soda or pop can, and miscellaneous junk are visible.]]\nPerson: This guy tears the labels off his cans, so he clearly understands they're going to be sorted somewhere - \nPerson: Yet in the same batch he includes a bottle with like an ounce of congealed juice in it.\nPerson: What an asshole.\nI worry a lot about what the people at the recycling center think of me.\n\n{{Title text: And given how much of my stuff they go through, they definitely know where I live.}}", "alt": "And given how much of my stuff they go through, they definitely know where I live.", "img": "https://imgs.xkcd.com/comics/recycling.png", "title": "Recycling", "day": "13"}