{"month": "10", "num": 966, "link": "", "year": "2011", "news": "", "safe_title": "Jet Fuel", "transcript": "[[Two people are having a conversation.]]\nPerson 1: 9\n11 was an inside job! Jet fuel can't burn hot enough to melt steel!\nPerson 2: Well, remember - jet fuel wasn't the only thing on those planes. They would've also carried tanks full of the mind-control agents airliners use to make chemtrails. Who \nknows\n what temperature that stuff burns at!\nPerson 1: Whoa. Good point!\n\n{{Title text: The 'controlled demolition' theory was concocted by the government to distract us. '9\n11 was an inside job' was an inside job!}}", "alt": "The 'controlled demolition' theory was concocted by the government to distract us. '9/11 was an inside job' was an inside job!", "img": "https://imgs.xkcd.com/comics/jet_fuel.png", "title": "Jet Fuel", "day": "19"}